hymns/__init__.py
hymns/data/__init__.py
hymns/data/base.py
hymns/data/eng.py
hymns/data/fra.py
hymns/data/por.py
hymns/data/spa.py
hymns-2025.9.5.dist-info/WHEEL
hymns-2025.9.5.dist-info/entry_points.txt
hymns-2025.9.5.dist-info/METADATA
hymns-2025.9.5.dist-info/RECORD
