Metadata-Version: 2.3
Name: hymns
Version: 2025.9.5
Summary: Compile a single PDF containing all the hymns in the collection "Hymns—For Home and Church"
Requires-Dist: httpx>=0.28.1
Requires-Dist: pymupdf>=1.26.1
Requires-Dist: pypng>=0.20220715.0
Requires-Dist: qrcode>=8.2
Requires-Python: >=3.13
Project-URL: Homepage, https://github.com/williamjacksn/hymns
Project-URL: Issues, https://github.com/williamjacksn/hymns/issues
